lodoo.py
lodoo-0.5.5.dist-info/licenses/LICENSE
lodoo-0.5.5.dist-info/METADATA
lodoo-0.5.5.dist-info/WHEEL
lodoo-0.5.5.dist-info/entry_points.txt
lodoo-0.5.5.dist-info/top_level.txt
lodoo-0.5.5.dist-info/RECORD
