Metadata-Version: 2.4
Name: lodoo
Version: 0.5.5
Summary: CLI to manage Local Odoo
Home-page: https://github.com/katyukha/LOdoo
Author: Dmytro Katyukha
Author-email: dmytro.katyukha@gmail.com
License: MPL 2.0
Project-URL: Bug Tracker, https://crnd.pro/requests
Keywords: odoo,local
Classifier: Development Status :: 3 - Alpha
Classifier: Intended Audience :: Developers
Classifier: License :: OSI Approved :: Mozilla Public License 2.0 (MPL 2.0)
Classifier: Programming Language :: Python
Classifier: Programming Language :: Python :: 2
Classifier: Programming Language :: Python :: 2.7
Classifier: Programming Language :: Python :: 3
Classifier: Programming Language :: Python :: 3.6
Classifier: Programming Language :: Python :: 3.7
Classifier: Programming Language :: Python :: 3.8
Classifier: Programming Language :: Python :: 3.9
Classifier: Programming Language :: Python :: 3.10
Classifier: Programming Language :: Python :: 3.11
Classifier: Programming Language :: Python :: 3.12
Classifier: Programming Language :: Python :: 3.13
Classifier: Programming Language :: Python :: Implementation :: CPython
Classifier: Topic :: Utilities
Requires-Python: >=2.7
License-File: LICENSE
Requires-Dist: click; python_version >= "3.7"
Requires-Dist: click<8.1; python_version < "3.7"
Requires-Dist: click<8.0; python_version < "3.5"
Dynamic: license-file
